{
   "android_play_store_link":"https://play.google.com/store/apps/details?id=com.antspace.stickers.superliga",
   "ios_app_store_link":"",
   "sticker_packs":[
      {
         "identifier":"eliminatoriasqatarf13",
         "name":"Eliminatorias F13",
         "animated_sticker_pack":false,
         "stickers":"30"
      },
      {
         "identifier":"eliminatoriasqatarf12",
         "name":"Eliminatorias F12",
         "animated_sticker_pack":false,
         "stickers":"23"
      },
      {
         "identifier":"eliminatoriasqatarf11",
         "name":"Eliminatorias F11",
         "animated_sticker_pack":false,
         "stickers":"30"
      },
      {
         "identifier":"riverplate2021",
         "name":"River Plate 2021",
         "animated_sticker_pack":false,
         "stickers":"28"
      },
      {
         "identifier":"sanlorenzo2021",
         "name":"San Lorenzo 2021",
         "animated_sticker_pack":false,
         "stickers":"29"
      },
      {
         "identifier":"independiente2021",
         "name":"Independiente 2021",
         "animated_sticker_pack":false,
         "stickers":"28"
      },
      {
         "identifier":"racingclub2021",
         "name":"Racing Club 2021",
         "animated_sticker_pack":false,
         "stickers":"29"
      },
      {
         "identifier":"newells2021",
         "name":"Newells Old Boys 2021",
         "animated_sticker_pack":false,
         "stickers":"30"
      },
      {
         "identifier":"rosariocentral2021",
         "name":"Rosario Central 2021",
         "animated_sticker_pack":false,
         "stickers":"30"
      },
            {
         "identifier":"argentina2021a",
         "name":"Argentina 2021 (1)",
         "animated_sticker_pack":false,
         "stickers":"24"
      },
      {
         "identifier":"argentina2021b",
         "name":"Argentina 2021 (2)",
         "animated_sticker_pack":false,
         "stickers":"29"
      },
      {
         "identifier":"argentina2021c",
         "name":"Argentina 2021 (3)",
         "animated_sticker_pack":false,
         "stickers":"27"
      },
      {
         "identifier":"argentina2021d",
         "name":"Argentina 2021 (4)",
         "animated_sticker_pack":false,
         "stickers":"27"
      },
      {
         "identifier":"argentina2021e",
         "name":"Argentina 2021 (5)",
         "animated_sticker_pack":false,
         "stickers":"17"
      },
      {
         "identifier":"bocajuniors2020",
         "name":"Boca Juniors",
         "animated_sticker_pack":false,
         "stickers":"27"
      },
      {
         "identifier":"colon2020",
         "name":"Colon",
         "animated_sticker_pack":false,
         "stickers":"27"
      },
      {
         "identifier":"estudianteslp2020",
         "name":"Estudiantes LP",
         "animated_sticker_pack":false,
         "stickers":"24"
      },
      {
         "identifier":"gimnasialp2020",
         "name":"Gimnasia LP",
         "animated_sticker_pack":false,
         "stickers":"27"
      },
      {
         "identifier":"huracan2020",
         "name":"Huracan",
         "animated_sticker_pack":false,
         "stickers":"20"
      },
      {
         "identifier":"independiente2020",
         "name":"Independiente 2020",
         "animated_sticker_pack":false,
         "stickers":"19"
      },
      {
         "identifier":"newells2020",
         "name":"Newells Old Boys 2020",
         "animated_sticker_pack":false,
         "stickers":"27"
      },
      {
         "identifier":"racingclub2020",
         "name":"Racing Club 2020",
         "animated_sticker_pack":false,
         "stickers":"28"
      },
      {
         "identifier":"rosariocentral2020",
         "name":"Rosario Central 2020",
         "animated_sticker_pack":false,
         "stickers":"30"
      },
      {
         "identifier":"sanlorenzo2020",
         "name":"San Lorenzo 2020",
         "animated_sticker_pack":false,
         "stickers":"30"
      },
      {
         "identifier":"union2020",
         "name":"Union",
         "animated_sticker_pack":false,
         "stickers":"19"
      },
      {
         "identifier":"velez2020",
         "name":"Velez Sarsfield",
         "animated_sticker_pack":false,
         "stickers":"30"
      },
      {
         "identifier":"riverplate2020",
         "name":"River Plate",
         "animated_sticker_pack":false,
         "stickers":"29"
      }
   ]
}